d2ssect/__init__.py
d2ssect/__main__.py
d2ssect/jellyfish.cpp
d2ssect/jellyfish.cpython-39-darwin.so
d2ssect/utils.py
d2ssect-0.0.6.dist-info/LICENSE
d2ssect-0.0.6.dist-info/METADATA
d2ssect-0.0.6.dist-info/WHEEL
d2ssect-0.0.6.dist-info/entry_points.txt
d2ssect-0.0.6.dist-info/top_level.txt
d2ssect-0.0.6.dist-info/RECORD
