Metadata-Version: 2.1
Name: d2ssect
Version: 0.0.6
Summary: Calculate d2s scores from short reads
Author-email: Jia Zhang <jia.zhang2@my.jcu.edu.au>, Ira Cooke <ira.cooke@jcu.edu.au>
License: The MIT License (MIT)
Keywords: feed,reader,tutorial
Classifier: License :: OSI Approved :: MIT License
Classifier: Programming Language :: Python
Classifier: Programming Language :: Python :: 3
Requires-Python: >=3.7
License-File: LICENSE
Requires-Dist: tomli ; python_version < "3.11"
